{
  "project_info": {
    "project_number": "572831008190",
    "project_id": "bloomyourday-dd658",
    "storage_bucket": "bloomyourday-dd658.firebasestorage.app"
  },
  "client": [
    {
      "client_info": {
        "mobilesdk_app_id": "1:572831008190:android:93a727da30da8171a965ef",
        "android_client_info": {
          "package_name": "com.example.vital_habit"
        }
      },
      "oauth_client": [
        {
          "client_id": "572831008190-4q3mulv08o5fu77sk9s9j4r4r4r1trkm.apps.googleusercontent.com",
          "client_type": 1,
          "android_info": {
            "package_name": "com.example.vital_habit",
            "certificate_hash": "c426882a0373ce331f37b49763e8b1b12d328606"
          }
        },
        {
          "client_id": "572831008190-1k6fibnnaf3fmamt2bl03426u9aa8d2a.apps.googleusercontent.com",
          "client_type": 3
        }
      ],
      "api_key": [
        {
          "current_key": "AIzaSyBsdNJ9gkTyl7dlmRUbkfYvdo1dksPGxLs"
        }
      ],
      "services": {
        "appinvite_service": {
          "other_platform_oauth_client": [
            {
              "client_id": "572831008190-1k6fibnnaf3fmamt2bl03426u9aa8d2a.apps.googleusercontent.com",
              "client_type": 3
            }
          ]
        }
      }
    }
  ],
  "configuration_version": "1"
}